entemplate/__init__.py
entemplate/_sqlite.py
entemplate/_template.py
entemplate/_template.pyi
entemplate/_utils.py
entemplate-0.1.0.dist-info/licenses/LICENSE
entemplate-0.1.0.dist-info/METADATA
entemplate-0.1.0.dist-info/WHEEL
entemplate-0.1.0.dist-info/top_level.txt
entemplate-0.1.0.dist-info/RECORD
