Metadata-Version: 2.4
Name: entemplate
Version: 0.1.0
Summary: Template string utilities
Classifier: License :: OSI Approved :: Apache Software License
Classifier: Operating System :: OS Independent
Classifier: Programming Language :: Python :: 3
Classifier: Programming Language :: Python :: 3.14
Requires-Python: >=3.14
License-File: LICENSE
Dynamic: license-file
